hub_to_lab/__init__.py
hub_to_lab/check.py
hub_to_lab/cli.py
hub_to_lab/config.py
hub_to_lab/github.py
hub_to_lab/gitlab.py
hub_to_lab/gitops.py
hub_to_lab-1.1.2.dist-info/LICENSE
hub_to_lab-1.1.2.dist-info/METADATA
hub_to_lab-1.1.2.dist-info/WHEEL
hub_to_lab-1.1.2.dist-info/entry_points.txt
hub_to_lab-1.1.2.dist-info/RECORD
