Metadata-Version: 2.3
Name: hub_to_lab
Version: 1.1.2
Summary: Copy a Github public repository to a Gitlab self-hosted project
License: MIT
Author: RobinWoods
Requires-Python: >=3.9,<4.0
Classifier: License :: OSI Approved :: MIT License
Classifier: Programming Language :: Python :: 3
Classifier: Programming Language :: Python :: 3.9
Classifier: Programming Language :: Python :: 3.10
Classifier: Programming Language :: Python :: 3.11
Classifier: Programming Language :: Python :: 3.12
Classifier: Programming Language :: Python :: 3.13
Requires-Dist: GitPython
Requires-Dist: platformdirs (>=4.3.8,<5.0.0)
Requires-Dist: python-dotenv
Requires-Dist: requests (==2.32.4)
Requires-Dist: rich
Requires-Dist: typer (>=0.16.0,<0.17.0)
